ruamel.auto-1.6.4-py3.10-nspkg.pth
ruamel/auto/__init__.py
ruamel/auto/__main__.py
ruamel/auto/auto.py
ruamel.auto-1.6.4.dist-info/LICENSE
ruamel.auto-1.6.4.dist-info/METADATA
ruamel.auto-1.6.4.dist-info/WHEEL
ruamel.auto-1.6.4.dist-info/entry_points.txt
ruamel.auto-1.6.4.dist-info/namespace_packages.txt
ruamel.auto-1.6.4.dist-info/top_level.txt
ruamel.auto-1.6.4.dist-info/RECORD
